{
  "cid": "omd-scheduler-m1-newer",
  "completed_at": "2026-07-15T14:18:55.684633+00:00",
  "gate": {
    "path": "gates/scheduler_fairness.yaml",
    "sha256": "7e249d738e941c2a56e6d8846ddc2d5b6489c95a0238d5471301c63bea19c4d1"
  },
  "negative": {
    "evidence_tier": "arrived",
    "gate_result": {
      "authenticated": null,
      "checks": [
        {
          "charged": true,
          "event": "orbit_requested",
          "got": 1,
          "grounding": "derived-self",
          "kind": "count",
          "op": "==",
          "optional": false,
          "passed": true,
          "pending": false,
          "settled_at": null,
          "strength": "bounded",
          "tautological": false,
          "verdict": "pend",
          "want": 1,
          "weight": 1.0,
          "where": {}
        },
        {
          "charged": false,
          "event": "orbit_pending",
          "got": 0,
          "grounding": "derived-self",
          "kind": "count",
          "op": "==",
          "optional": false,
          "passed": false,
          "pending": false,
          "settled_at": null,
          "strength": "bounded",
          "tautological": false,
          "verdict": "pend",
          "want": 1,
          "weight": 1.0,
          "where": {}
        },
        {
          "charged": true,
          "firsts": {
            "orbit_pending": null,
            "orbit_requested": 1784125135652649
          },
          "grounding": "derived-self",
          "kind": "must_order",
          "missing": [
            "orbit_pending"
          ],
          "must_order": [
            "orbit_requested",
            "orbit_pending"
          ],
          "optional": false,
          "ordered": false,
          "passed": false,
          "pending": false,
          "settled_at": null,
          "strength": "ordered",
          "verdict": "pend",
          "weight": 1.0
        }
      ],
      "cid": "omd-scheduler-m1-newer",
      "complete": true,
      "ok": false,
      "optional_failed": [],
      "oracle": {
        "corroborated": 0,
        "derived_self": 3,
        "emit_backend": "MemoryBackend",
        "emit_identity": "MemoryBackend",
        "enforced": false,
        "forbid_errors": false,
        "gating": 3,
        "relocated": 0,
        "signature_enforced": false,
        "single_authority": true
      },
      "pending_failed": [],
      "pending_satisfied": [],
      "probe_reachable": true,
      "reachable": true,
      "scope": {
        "asserts_anything": true,
        "by_strength": {
          "bounded": 2,
          "ordered": 1
        },
        "charge_ratio": 0.6666666666666666,
        "charged": 2,
        "gating": 3,
        "named_event_types": 1,
        "observed_event_types": 4,
        "optional": 0,
        "pending": 0,
        "stream_coverage": 0.25,
        "total": 3,
        "unasserted_observed": [
          "orbit_granted",
          "orbit_released",
          "scheduler_fairness_probe_completed"
        ],
        "uncharged": [
          "orbit_pending"
        ]
      },
      "unauthenticated": false,
      "uncorroborated": false,
      "vacuous": false
    },
    "observation": {
      "after_holder_release": {
        "newer": "HELD",
        "older": "PENDING"
      },
      "cid": "omd-scheduler-m1-newer",
      "final": {
        "newer": "RELEASED",
        "older": "RELEASED"
      },
      "holder_state": "HELD",
      "newer_claim_state": "HELD",
      "newer_created_at": 1784125135.65274,
      "newer_granted_while_older_pending": true,
      "newer_priority": 0,
      "no_overtaking_passed": false,
      "older_arrived_first": true,
      "older_created_at": 1784125135.652417,
      "older_priority": 10,
      "older_waiter_state": "PENDING",
      "pending_predecessor_bypass_injected": true,
      "schema": "omd.m1.fair-admission-observation.v1",
      "store_readback_complete": true
    },
    "pending_predecessor_bypass_injected": true
  },
  "positive": {
    "evidence_tier": "arrived",
    "gate_result": {
      "authenticated": null,
      "checks": [
        {
          "charged": true,
          "event": "orbit_requested",
          "got": 1,
          "grounding": "derived-self",
          "kind": "count",
          "op": "==",
          "optional": false,
          "passed": true,
          "pending": false,
          "settled_at": null,
          "strength": "bounded",
          "tautological": false,
          "verdict": "pend",
          "want": 1,
          "weight": 1.0,
          "where": {}
        },
        {
          "charged": true,
          "event": "orbit_pending",
          "got": 1,
          "grounding": "derived-self",
          "kind": "count",
          "op": "==",
          "optional": false,
          "passed": true,
          "pending": false,
          "settled_at": null,
          "strength": "bounded",
          "tautological": false,
          "verdict": "pend",
          "want": 1,
          "weight": 1.0,
          "where": {}
        },
        {
          "charged": true,
          "firsts": {
            "orbit_pending": 1784125135644740,
            "orbit_requested": 1784125135644546
          },
          "grounding": "derived-self",
          "kind": "must_order",
          "missing": [],
          "must_order": [
            "orbit_requested",
            "orbit_pending"
          ],
          "optional": false,
          "ordered": true,
          "passed": true,
          "pending": false,
          "settled_at": 1,
          "strength": "ordered",
          "verdict": "sat",
          "weight": 1.0
        }
      ],
      "cid": "omd-scheduler-m1-newer",
      "complete": true,
      "ok": true,
      "optional_failed": [],
      "oracle": {
        "corroborated": 0,
        "derived_self": 3,
        "emit_backend": "MemoryBackend",
        "emit_identity": "MemoryBackend",
        "enforced": false,
        "forbid_errors": false,
        "gating": 3,
        "relocated": 0,
        "signature_enforced": false,
        "single_authority": true
      },
      "pending_failed": [],
      "pending_satisfied": [],
      "probe_reachable": true,
      "reachable": true,
      "scope": {
        "asserts_anything": true,
        "by_strength": {
          "bounded": 2,
          "ordered": 1
        },
        "charge_ratio": 1.0,
        "charged": 3,
        "gating": 3,
        "named_event_types": 2,
        "observed_event_types": 5,
        "optional": 0,
        "pending": 0,
        "stream_coverage": 0.4,
        "total": 3,
        "unasserted_observed": [
          "orbit_granted",
          "orbit_released",
          "scheduler_fairness_probe_completed"
        ],
        "uncharged": []
      },
      "unauthenticated": false,
      "uncorroborated": false,
      "vacuous": false
    },
    "observation": {
      "after_holder_release": {
        "newer": "PENDING",
        "older": "HELD"
      },
      "cid": "omd-scheduler-m1-newer",
      "final": {
        "newer": "RELEASED",
        "older": "RELEASED"
      },
      "holder_state": "HELD",
      "newer_claim_state": "PENDING",
      "newer_created_at": 1784125135.644663,
      "newer_granted_while_older_pending": false,
      "newer_priority": 0,
      "no_overtaking_passed": true,
      "older_arrived_first": true,
      "older_created_at": 1784125135.6442492,
      "older_priority": 10,
      "older_waiter_state": "PENDING",
      "pending_predecessor_bypass_injected": false,
      "schema": "omd.m1.fair-admission-observation.v1",
      "store_readback_complete": true
    },
    "pending_predecessor_bypass_injected": false
  },
  "producer": {
    "command": "/Users/lagyeongjun/CD/omd/.venv/bin/python /Users/lagyeongjun/CD/omd/benchmarks/produce_scheduler_m1_receipt.py --gate gates/scheduler_fairness.yaml --cid omd-scheduler-m1-newer --output evidence/omd_scheduler_m1/ooptdd_run.json --receipt-output evidence/omd_scheduler_m1/ooptdd_receipt.json",
    "cwd": "/Users/lagyeongjun/CD/omd",
    "entrypoint": "benchmarks.produce_scheduler_m1_receipt:produce",
    "entrypoint_path": "benchmarks/omd_scheduler_m1.py",
    "entrypoint_sha256": "b7e8dc77f19d4d472a976a73ef073479edadcd42169d121f9ee93498f93d2bc1",
    "exit_code": 0,
    "git_head": "a1d2ddde2a337425162eb8f6457bbc0920892480",
    "path": "benchmarks/produce_scheduler_m1_receipt.py",
    "real_code_path": true,
    "scenario_entrypoint": "benchmarks.omd_scheduler_m1:run_ooptdd",
    "sha256": "501a0386001caec199035eb9b5b6f1fec8c315fbe3a131c6fd6cd0813d0cb8b1",
    "source_symbol": "produce"
  },
  "restored_positive": {
    "evidence_tier": "arrived",
    "gate_result": {
      "authenticated": null,
      "checks": [
        {
          "charged": true,
          "event": "orbit_requested",
          "got": 1,
          "grounding": "derived-self",
          "kind": "count",
          "op": "==",
          "optional": false,
          "passed": true,
          "pending": false,
          "settled_at": null,
          "strength": "bounded",
          "tautological": false,
          "verdict": "pend",
          "want": 1,
          "weight": 1.0,
          "where": {}
        },
        {
          "charged": true,
          "event": "orbit_pending",
          "got": 1,
          "grounding": "derived-self",
          "kind": "count",
          "op": "==",
          "optional": false,
          "passed": true,
          "pending": false,
          "settled_at": null,
          "strength": "bounded",
          "tautological": false,
          "verdict": "pend",
          "want": 1,
          "weight": 1.0,
          "where": {}
        },
        {
          "charged": true,
          "firsts": {
            "orbit_pending": 1784125135660803,
            "orbit_requested": 1784125135660651
          },
          "grounding": "derived-self",
          "kind": "must_order",
          "missing": [],
          "must_order": [
            "orbit_requested",
            "orbit_pending"
          ],
          "optional": false,
          "ordered": true,
          "passed": true,
          "pending": false,
          "settled_at": 1,
          "strength": "ordered",
          "verdict": "sat",
          "weight": 1.0
        }
      ],
      "cid": "omd-scheduler-m1-newer",
      "complete": true,
      "ok": true,
      "optional_failed": [],
      "oracle": {
        "corroborated": 0,
        "derived_self": 3,
        "emit_backend": "MemoryBackend",
        "emit_identity": "MemoryBackend",
        "enforced": false,
        "forbid_errors": false,
        "gating": 3,
        "relocated": 0,
        "signature_enforced": false,
        "single_authority": true
      },
      "pending_failed": [],
      "pending_satisfied": [],
      "probe_reachable": true,
      "reachable": true,
      "scope": {
        "asserts_anything": true,
        "by_strength": {
          "bounded": 2,
          "ordered": 1
        },
        "charge_ratio": 1.0,
        "charged": 3,
        "gating": 3,
        "named_event_types": 2,
        "observed_event_types": 5,
        "optional": 0,
        "pending": 0,
        "stream_coverage": 0.4,
        "total": 3,
        "unasserted_observed": [
          "orbit_granted",
          "orbit_released",
          "scheduler_fairness_probe_completed"
        ],
        "uncharged": []
      },
      "unauthenticated": false,
      "uncorroborated": false,
      "vacuous": false
    },
    "observation": {
      "after_holder_release": {
        "newer": "PENDING",
        "older": "HELD"
      },
      "cid": "omd-scheduler-m1-newer",
      "final": {
        "newer": "RELEASED",
        "older": "RELEASED"
      },
      "holder_state": "HELD",
      "newer_claim_state": "PENDING",
      "newer_created_at": 1784125135.660744,
      "newer_granted_while_older_pending": false,
      "newer_priority": 0,
      "no_overtaking_passed": true,
      "older_arrived_first": true,
      "older_created_at": 1784125135.660411,
      "older_priority": 10,
      "older_waiter_state": "PENDING",
      "pending_predecessor_bypass_injected": false,
      "schema": "omd.m1.fair-admission-observation.v1",
      "store_readback_complete": true
    },
    "pending_predecessor_bypass_injected": false
  },
  "schema": "omd-scheduler-m1-ooptdd-run/v1",
  "spec": {
    "locked_before_positive_run": true,
    "path": "spec/omd_scheduler_m1_ooptdd.yaml",
    "sha256": "586d8b7e92e7f1974c7acbb1d12969337f57c5f678670243e215b46bb8c2d995"
  },
  "subject": {
    "admission_path": "omd_server/admission.py",
    "admission_sha256": "05ef13014b60e3ef318ebecd14bf5bd85ab30d8df8918150dc025bc67593bdd2",
    "core_path": "omd_server/core.py",
    "core_sha256": "6ec1abddffff80af2befc809c27cf8d07062b79009ee40ef767bae2b3e97f7e5",
    "git_head_before_evidence_commit": "a1d2ddde2a337425162eb8f6457bbc0920892480"
  }
}
